heatmap_by_2_dimensions/__init__.py
heatmap_by_2_dimensions/heatmap_by_2_dimensions.py
linear_forecast_lib/__init__.py
linear_forecast_lib/linear_forecast.py
pareto_chart_lib/__init__.py
pareto_chart_lib/pareto.py
analytics_huytln-0.3.2.dist-info/METADATA
analytics_huytln-0.3.2.dist-info/WHEEL
analytics_huytln-0.3.2.dist-info/top_level.txt
analytics_huytln-0.3.2.dist-info/RECORD
