Metadata-Version: 2.1
Name: analytics_huytln
Version: 0.3.2
Summary: A simple library to plot insightful charts
Home-page: https://github.com/trinhlenhathuy/analytics_huytln
Author: Huy Trịnh Lê Nhật
Author-email: trinhlenhathuy@gmail.com
License: MIT
Keywords: data visualization,charts,pareto,heatmap
Classifier: Programming Language :: Python :: 3
Classifier: License :: OSI Approved :: MIT License
Classifier: Operating System :: OS Independent
Requires-Python: >=3.6
Requires-Dist: pandas
Requires-Dist: matplotlib
